flipdigitclock/__init__.py
flipdigitclock/flipdigitclock.py
flipdigitclock-0.1.0.dist-info/LICENSE
flipdigitclock-0.1.0.dist-info/METADATA
flipdigitclock-0.1.0.dist-info/WHEEL
flipdigitclock-0.1.0.dist-info/top_level.txt
flipdigitclock-0.1.0.dist-info/RECORD
