Metadata-Version: 2.1
Name: flipdigitclock
Version: 0.1.0
Summary: Flip digit clock library
Home-page: https://github.com/lucblender/FlipDigitClockPython
Author: Lucas Bonvin
License: MIT
Platform: UNKNOWN
Classifier: Programming Language :: Python :: 3
Classifier: License :: OSI Approved :: MIT License
Classifier: Operating System :: OS Independent
Requires-Python: >=3.6
Requires-Dist: RPi.GPIO
